OldIsoSpecCppPy
OldIsoSpecPy
