Metadata-Version: 2.4
Name: OldIsoSpecPy
Version: 1.0.14
Summary: Python interface to IsoSpec++ isotopic envelope calculator library
Home-page: http://matteolacki.github.io/IsoSpec/
Author: Mateusz Lacki & Michal Startek
Author-email: matteo.lacki@gmail.com
License: 2-clause BSD
Keywords: isotopic envelope
Classifier: Development Status :: 5 - Production/Stable
Classifier: Intended Audience :: Science/Research
Classifier: Topic :: Scientific/Engineering :: Chemistry
Classifier: License :: OSI Approved :: BSD License
Classifier: Programming Language :: Python :: 2
Classifier: Programming Language :: Python :: 2.6
Classifier: Programming Language :: Python :: 2.7
Classifier: Programming Language :: Python :: 3
Classifier: Programming Language :: Python :: 3.2
Classifier: Programming Language :: Python :: 3.3
Classifier: Programming Language :: Python :: 3.4
Requires-Dist: numpy
Requires-Dist: cffi
Dynamic: author
Dynamic: author-email
Dynamic: classifier
Dynamic: description
Dynamic: home-page
Dynamic: keywords
Dynamic: license
Dynamic: requires-dist
Dynamic: summary
